nifti_overlay/__init__.py
nifti_overlay/__main__.py
nifti_overlay/__version__.py
nifti_overlay/core.py
nifti_overlay/image.py
nifti_overlay/multiimage.py
nifti_overlay-0.0.1.dist-info/LICENSE
nifti_overlay-0.0.1.dist-info/METADATA
nifti_overlay-0.0.1.dist-info/WHEEL
nifti_overlay-0.0.1.dist-info/entry_points.txt
nifti_overlay-0.0.1.dist-info/top_level.txt
nifti_overlay-0.0.1.dist-info/RECORD
