Metadata-Version: 2.2
Name: nifti_overlay
Version: 0.0.1
Summary: A program for creating tiled images of volumetric neuorimaging data.
Home-page: https://github.com/earnestt1234/nifti_overlay
Author: Tom Earnest
Author-email: Tom Earnest <earnestt1234@gmail.com>
License: MIT
Project-URL: Homepage, https://github.com/earnestt1234/nifti_overlay
Requires-Python: >=3.10
License-File: LICENSE
Requires-Dist: matplotlib>=3.2
Requires-Dist: nibabel>=3.2
Requires-Dist: numpy>=1.2
Requires-Dist: scikit-image>=0.24.0
Dynamic: author
Dynamic: home-page
Dynamic: requires-python
